[
  {
    "_id": "58faf063e73eea13d46fedbe",
    "time": "2017-03-31T22:54:18",
    "whisper_from": false,
    "whisper_to": "Dorkles",
  },
  {
	"_id": "58faf063e73eea13d46fedc1",
	"time": "2017-03-31T23:00:57",
	"whisper_from": "Dorkles",
	"whisper_to": false,
  }
  {
    "_id": "58faf063e73eea13d46fedbe",
    "time": "2017-03-31T22:54:18",
    "whisper_from": false,
    "whisper_to": "Kitty-Cat",
  },
  {
	"_id": "58faf063e73eea13d46fedc1",
	"time": "2017-03-31T23:00:57",
	"whisper_from": "Kitty-Cat",
	"whisper_to": false,
  }  
]